blockingpy/__init__.py
blockingpy/annoy_blocker.py
blockingpy/base.py
blockingpy/blocker.py
blockingpy/blocking_result.py
blockingpy/controls.py
blockingpy/data_handler.py
blockingpy/datasets/__init__.py
blockingpy/datasets/base.py
blockingpy/datasets/utils.py
blockingpy/faiss_blocker.py
blockingpy/gpu_faiss_blocker.py
blockingpy/helper_functions.py
blockingpy/hnsw_blocker.py
blockingpy/mlpack_blocker.py
blockingpy/nnd_blocker.py
blockingpy/py.typed
blockingpy/text_encoders/__init__.py
blockingpy/text_encoders/base.py
blockingpy/text_encoders/embedding_encoder.py
blockingpy/text_encoders/shingle_encoder.py
blockingpy/text_encoders/text_transformer.py
blockingpy/voyager_blocker.py
blockingpy_core-0.2.8.dist-info/METADATA
blockingpy_core-0.2.8.dist-info/WHEEL
blockingpy_core-0.2.8.dist-info/RECORD
