Metadata-Version: 2.4
Name: blockingpy-core
Version: 0.2.8
Summary: Core library for BlockingPy.
License: MIT
Keywords: record-linkage,deduplication,ANN,blocking,data-matching
Author: Tymoteusz Strojny
Author-email: tymek.strojny@gmail.com
Requires-Python: >=3.10,<3.13
Classifier: Development Status :: 3 - Alpha
Classifier: Intended Audience :: Science/Research
Classifier: License :: OSI Approved :: MIT License
Classifier: Programming Language :: Python :: 3
Classifier: Programming Language :: Python :: 3.10
Classifier: Programming Language :: Python :: 3.11
Classifier: Programming Language :: Python :: 3.12
Classifier: Programming Language :: Python :: 3.13
Classifier: Topic :: Scientific/Engineering :: Information Analysis
Classifier: Topic :: Software Development :: Libraries :: Python Modules
Provides-Extra: faiss
Requires-Dist: annoy (>=1.17.3,<2.0.0)
Requires-Dist: faiss-cpu (>=1.7.4) ; extra == "faiss"
Requires-Dist: hnswlib (>=0.8.0,<0.9.0)
Requires-Dist: igraph (>=0.11.9,<0.12.0)
Requires-Dist: mlpack (>=4.4.0,<4.6.1)
Requires-Dist: model2vec (>=0.4.1,<1.0.0)
Requires-Dist: nltk (>=3.9.1,<4.0.0)
Requires-Dist: numpy (>=1.26.4,<2.0.0)
Requires-Dist: pandas (>=2.2.0,<3.0.0)
Requires-Dist: pooch (>=1.8.2,<2.0.0)
Requires-Dist: pynndescent (>=0.5.13,<0.6.0)
Requires-Dist: scikit-learn (>=1.5.2,<2.0.0)
Requires-Dist: scipy (>=1.5.0)
Requires-Dist: voyager (>=2.0.9,<3.0.0)
Project-URL: Bug Tracker, https://github.com/ncn-foreigners/BlockingPy/issues
Project-URL: Documentation, https://blockingpy.readthedocs.io/en/latest/
Project-URL: Funding, https://www.ncn.gov.pl
Project-URL: Repository, https://github.com/ncn-foreigners/BlockingPy
